zlata_say/__init__.py
zlata_say/__main__.py
zlata_say/core.py
zlata_say-0.1.0.dist-info/licenses/LICENSE
zlata_say-0.1.0.dist-info/METADATA
zlata_say-0.1.0.dist-info/WHEEL
zlata_say-0.1.0.dist-info/entry_points.txt
zlata_say-0.1.0.dist-info/top_level.txt
zlata_say-0.1.0.dist-info/RECORD
